villaPriceDatabase/__init__.py
villaPriceDatabase/_nbdev.py
villaPriceDatabase/database.py
villaPriceDatabase/database2.py
villaPriceDatabase/helper.py
villaPriceDatabase/query.py
villaPriceDatabase/s3.py
villaPriceDatabase/s3gz.py
villaPriceDatabase/update.py
villaPriceDatabase-0.0.17.dist-info/LICENSE
villaPriceDatabase-0.0.17.dist-info/METADATA
villaPriceDatabase-0.0.17.dist-info/WHEEL
villaPriceDatabase-0.0.17.dist-info/top_level.txt
villaPriceDatabase-0.0.17.dist-info/RECORD
