Metadata-Version: 2.1
Name: villaPriceDatabase
Version: 0.0.17
Summary: price database management functions
Home-page: https://github.com/thanakijwanavit/villaPriceDatabase/tree/master/
Author: Nic Wanavit
Author-email: nwanavit@hatari.cc
License: Apache Software License 2.0
Keywords: price database
Platform: UNKNOWN
Classifier: Development Status :: 3 - Alpha
Classifier: Intended Audience :: Developers
Classifier: License :: OSI Approved :: Apache Software License
Classifier: Natural Language :: English
Classifier: Programming Language :: Python :: 3.6
Classifier: Programming Language :: Python :: 3.7
Classifier: Programming Language :: Python :: 3.8
Requires-Python: >=3.6
License-File: LICENSE
Requires-Dist: awsSchema
Requires-Dist: boto3
Requires-Dist: pandas
Requires-Dist: pynamodb-dax
Requires-Dist: s3bz
Requires-Dist: lambdasdk
